[
  {
    "name": "auth_token",
    "value": "8a3d2e672f896695bc96bea2044a2fa328c6a836",
    "domain": ".x.com",
    "path": "/",
    "secure": true,
    "expires": null,
    "rest": {}
  },
  {
    "name": "gt",
    "value": "2017904043058733243",
    "domain": ".x.com",
    "path": "/",
    "secure": true,
    "expires": null,
    "rest": {}
  },
  {
    "name": "__cf_bm",
    "value": "sEk_BItBvvpxYuG1qkfcLBJjD9xLvEtmBEHyU3zPeok-1769940789.6859279-1.0.1.1-KZpV_4ay_E0VqE2wFnTe77EhatDv2QSIqRyJ6UjDCti5kWHvze3w8Fa.QgrRDY_1GLWOJE8Y58R_9DJz3kXaA_m5x5fRbYEeHlUObbKizwjbsket8DjPHJ2P9Ic_usKj",
    "domain": ".x.com",
    "path": "/",
    "secure": true,
    "expires": null,
    "rest": {}
  },
  {
    "name": "ct0",
    "value": "5e879c0f6d799fdeaac8f2db682c5e63f563e9e2ecde56f9dacc9d77b7edf0bf8b92d3d7df4ebebc31a4d3cc239d3840e5f06f4ece1d71eac175146cc919504eedd5e7788118f7aad5f4dabe8f69df3f",
    "domain": ".x.com",
    "path": "/",
    "secure": true,
    "expires": null,
    "rest": {}
  },
  {
    "name": "guest_id",
    "value": "v1%3A176994078694456618",
    "domain": ".x.com",
    "path": "/",
    "secure": true,
    "expires": null,
    "rest": {}
  },
  {
    "name": "guest_id_ads",
    "value": "v1%3A176994078694456618",
    "domain": ".x.com",
    "path": "/",
    "secure": true,
    "expires": null,
    "rest": {}
  },
  {
    "name": "guest_id_marketing",
    "value": "v1%3A176994078694456618",
    "domain": ".x.com",
    "path": "/",
    "secure": true,
    "expires": null,
    "rest": {}
  },
  {
    "name": "personalization_id",
    "value": "v1_pBWSGbMh3rgmrDsxyXj0QQ==",
    "domain": ".x.com",
    "path": "/",
    "secure": true,
    "expires": null,
    "rest": {}
  },
  {
    "name": "twid",
    "value": "u%3D2942014587",
    "domain": ".x.com",
    "path": "/",
    "secure": true,
    "expires": null,
    "rest": {}
  }
]