[
    {
        "name": "guest_id_marketing",
        "value": "v1%3A176365354021778793"
    },
    {
        "name": "guest_id_ads",
        "value": "v1%3A176365354021778793"
    },
    {
        "name": "personalization_id",
        "value": "\"v1_8CwCc35/7/VsWqP4tu/GpA==\""
    },
    {
        "name": "guest_id",
        "value": "v1%3A176365354021778793"
    },
    {
        "name": "__cf_bm",
        "value": "mlM94Hw7tSvF9NKhPr64t6uXfX.ZjeOL7aSY9e805EE-1763653543.5978549-1.0.1.1-LFy1.6xcvMAap.G8r.pADTRFSbAYETj66LoGW80UrKTBXr1ghX_QCu6hTVV4YT3rTQOEDoMEtCS.2PAYaG_Q9WP_zrYwoBvozTebNN5lAIp37YDWdgqsCkh4CuEHMOUq"
    },
    {
        "name": "twid",
        "value": "u%3D757538603266347008"
    },
    {
        "name": "ct0",
        "value": "cb964058a6fc5aefa394f7d69d6c8dc15a4e83d3fd313723d5d25067dba20874cbcc0e912536624ac51a999b4da15327ac00c07c85cb9f2c8c8a945edae47866900779eb6b687a35872e049cd183ab6d"
    },
    {
        "name": "gt",
        "value": "1991533421772832963"
    },
    {
        "name": "auth_token",
        "value": "2b04d63d694ff3221b4384463a4795716c3ce05d"
    }
]