[
  {
    "name": "auth_token",
    "value": "77065821ac028a620c27e68c0bf13e3762c274fd",
    "domain": ".x.com",
    "path": "/",
    "secure": true,
    "expires": null,
    "rest": {}
  },
  {
    "name": "gt",
    "value": "2017972585053782034",
    "domain": ".x.com",
    "path": "/",
    "secure": true,
    "expires": null,
    "rest": {}
  },
  {
    "name": "__cf_bm",
    "value": "D5E8BMLnnZOhQAd1QLKv3bem.78Cszx0Ur3oq.EHKYI-1769957131.4271271-1.0.1.1-Zb7A_ErehzcVgjYrw14klD68Bt9ZhiVot0DjK2KnbaprQMHgcKneuBX9QsNp3ZdVUadendooa9X2y3XE_sXXHrDWJvjyBNJKtWx95d.YqGwtPTpoqjBsl8tazn99rLF6",
    "domain": ".x.com",
    "path": "/",
    "secure": true,
    "expires": null,
    "rest": {}
  },
  {
    "name": "ct0",
    "value": "9a393c853c1aabb16a2cbb52578f363404ee4b91b19a8d155cc4e9ba2f5ae0be45bd4d40bcc02ca171f1e3ac6be43d175936f3c49f97ae1a1a38ff3e47ecc0ff5c17ed43b3abb494e010d58517042cc7",
    "domain": ".x.com",
    "path": "/",
    "secure": true,
    "expires": null,
    "rest": {}
  },
  {
    "name": "guest_id",
    "value": "v1%3A176995712839275738",
    "domain": ".x.com",
    "path": "/",
    "secure": true,
    "expires": null,
    "rest": {}
  },
  {
    "name": "guest_id_ads",
    "value": "v1%3A176995712839275738",
    "domain": ".x.com",
    "path": "/",
    "secure": true,
    "expires": null,
    "rest": {}
  },
  {
    "name": "guest_id_marketing",
    "value": "v1%3A176995712839275738",
    "domain": ".x.com",
    "path": "/",
    "secure": true,
    "expires": null,
    "rest": {}
  },
  {
    "name": "personalization_id",
    "value": "v1_u+UFiourAu37uf0oCn7ivQ==",
    "domain": ".x.com",
    "path": "/",
    "secure": true,
    "expires": null,
    "rest": {}
  },
  {
    "name": "twid",
    "value": "u%3D838602687012810752",
    "domain": ".x.com",
    "path": "/",
    "secure": true,
    "expires": null,
    "rest": {}
  }
]