[
    {
        "name": "guest_id_marketing",
        "value": "v1%3A176365131094638202"
    },
    {
        "name": "guest_id_ads",
        "value": "v1%3A176365131094638202"
    },
    {
        "name": "personalization_id",
        "value": "\"v1_7hO+CHitCciBfujtV9be5w==\""
    },
    {
        "name": "guest_id",
        "value": "v1%3A176365131094638202"
    },
    {
        "name": "__cf_bm",
        "value": "XSSOYJFW.4H2q4px8ycNJRi6E142rTdCvyg8NE4MWI8-1763651319.253977-1.0.1.1-9db1oLXMSX4_ea6CO75J.5lyURnU_zYqu0.aux71Tax82V_w228K1B7DSeaa991bejmS6LVXcWBHV_RotfC36MmioVFTufWuTKOz5c8b5_QaLZoFfzHC7K.VrugJsf1q"
    },
    {
        "name": "twid",
        "value": "u%3D785038505504182272"
    },
    {
        "name": "ct0",
        "value": "2e6b9d3a5ff2e0e83018bddf9da9a3dcedfd7ef59202a55b1c8f23579f9473363d27a4a389e22e1b5cc08b5337043ed888ea73ee136465dca24ffd4d1033a1291b4d625058db55653529f3089600c7c5"
    },
    {
        "name": "gt",
        "value": "1991524091933736981"
    },
    {
        "name": "auth_token",
        "value": "1a22dc29b1cd5c7cb1c6da38282d4a474d6240af"
    }
]