[
  {
    "name": "auth_token",
    "value": "5d0c9713b9943f269ad90c9eb761cdfcf9ca2566",
    "domain": ".x.com",
    "path": "/",
    "secure": true,
    "expires": null,
    "rest": {}
  },
  {
    "name": "gt",
    "value": "2017902267324572152",
    "domain": ".x.com",
    "path": "/",
    "secure": true,
    "expires": null,
    "rest": {}
  },
  {
    "name": "ct0",
    "value": "2b684ed150f7ec01299bd41e3e19defd8c250df07ed7b52ee806e6d155fcb0966fac6d58efcf4705cebddfdea34f72bede64efc22fb06f07ebf56634aad0ccdb4b3e4b4b96cf527ed879893f7c130fb8",
    "domain": ".x.com",
    "path": "/",
    "secure": true,
    "expires": null,
    "rest": {}
  },
  {
    "name": "guest_id",
    "value": "v1%3A176994036282752979",
    "domain": ".x.com",
    "path": "/",
    "secure": true,
    "expires": null,
    "rest": {}
  },
  {
    "name": "guest_id_ads",
    "value": "v1%3A176994036282752979",
    "domain": ".x.com",
    "path": "/",
    "secure": true,
    "expires": null,
    "rest": {}
  },
  {
    "name": "guest_id_marketing",
    "value": "v1%3A176994036282752979",
    "domain": ".x.com",
    "path": "/",
    "secure": true,
    "expires": null,
    "rest": {}
  },
  {
    "name": "personalization_id",
    "value": "v1_QecAYwOf80kfy8d0UD2GfQ==",
    "domain": ".x.com",
    "path": "/",
    "secure": true,
    "expires": null,
    "rest": {}
  },
  {
    "name": "twid",
    "value": "u%3D594343366",
    "domain": ".x.com",
    "path": "/",
    "secure": true,
    "expires": null,
    "rest": {}
  }
]